mcli/__init__.py
mcli/main.py
mercury_sdk/__init__.py
mercury_sdk/http/__init__.py
mercury_sdk/http/active.py
mercury_sdk/http/base.py
mercury_sdk/http/inventory.py
mercury_sdk/http/query.py
mercury_sdk/http/rpc.py
mercury_sdk/mcli/__init__.py
mercury_sdk/mcli/configuration.py
mercury_sdk/mcli/main.py
mercury_sdk/mcli/operations.py
mercury_sdk/mcli/output.py
mercury_sdk/mcli/press.py
mercury_sdk/mcli/shell.py
mercury_sdk/mcli/auth/__init__.py
mercury_sdk/mcli/auth/auth.py
mercury_sdk/mcli/auth/keystone.py
mercury_sdk/press_templates/__init__.py
mercury_sdk/rpc/__init__.py
mercury_sdk/rpc/job.py
mercury_sdk/rpc/task.py
mercury_sdk-0.0.12.dist-info/DESCRIPTION.rst
mercury_sdk-0.0.12.dist-info/METADATA
mercury_sdk-0.0.12.dist-info/RECORD
mercury_sdk-0.0.12.dist-info/WHEEL
mercury_sdk-0.0.12.dist-info/entry_points.txt
mercury_sdk-0.0.12.dist-info/metadata.json
mercury_sdk-0.0.12.dist-info/pbr.json
mercury_sdk-0.0.12.dist-info/top_level.txt
