Metadata-Version: 2.0
Name: mercury-sdk
Version: 0.0.12
Summary: Mercury HTTP client libraries, cli, and utilities
Home-page: http://www.mercurysoft.io
Author: Jared Rodriguez
Author-email: jared.rodriguez@rackspace.com
License: Apache-2.0
Platform: UNKNOWN
Requires-Dist: requests
Requires-Dist: PyYaml
Requires-Dist: cmd2
Requires-Dist: python-dateutil
Requires-Dist: colorama
